<?xml version="1.0" encoding="utf-8"?>
<odoo>
    <!-- Main Menu -->
    <menuitem id="menu_real_estate_root"
              name="Real Estate"
              web_icon="real_estate_management_v2,static/description/icon.png"
              sequence="10"/>
    
    <!-- Properties Menu -->
    <menuitem id="menu_real_estate_properties"
              name="Properties"
              parent="menu_real_estate_root"
              sequence="10"/>
    
    <menuitem id="menu_property_property"
              name="Properties"
              parent="menu_real_estate_properties"
              action="action_property_property"
              sequence="10"/>
    
    <menuitem id="menu_property_offer"
              name="Offers"
              parent="menu_real_estate_properties"
              action="action_property_offer"
              sequence="20"/>
    
    <menuitem id="menu_property_sale"
              name="Sales"
              parent="menu_real_estate_properties"
              action="action_property_sale"
              sequence="30"/>
    
    <!-- Configuration Menu -->
    <menuitem id="menu_real_estate_configuration"
              name="Configuration"
              parent="menu_real_estate_root"
              sequence="100"/>
    
    <menuitem id="menu_property_type"
              name="Property Types"
              parent="menu_real_estate_configuration"
              action="action_property_type"
              sequence="10"/>
    
    <menuitem id="menu_property_project"
              name="Projects"
              parent="menu_real_estate_configuration"
              action="action_property_project"
              sequence="20"/>
    
    <menuitem id="menu_property_tag"
              name="Tags"
              parent="menu_real_estate_configuration"
              action="action_property_tag"
              sequence="30"/>
    
    <!-- Reporting Menu -->
    <menuitem id="menu_real_estate_reporting"
              name="Reporting"
              parent="menu_real_estate_root"
              sequence="50"/>
    
    <menuitem id="menu_property_analysis"
              name="Property Analysis"
              parent="menu_real_estate_reporting"
              action="action_property_analysis_report"
              sequence="10"/>
    
    <menuitem id="menu_sales_analysis"
              name="Sales Analysis"
              parent="menu_real_estate_reporting"
              action="action_property_sales_analysis_report"
              sequence="20"/>
    
    <!-- Commission Menu -->
    <menuitem id="menu_real_estate_commission"
              name="Commissions"
              parent="menu_real_estate_root"
              sequence="40"/>
    
    <menuitem id="menu_internal_commission"
              name="Internal Commissions"
              parent="menu_real_estate_commission"
              action="action_internal_commission"
              sequence="10"/>
</odoo>